OpenSeesHpy/OpenSeesH.pyd
OpenSeesHpy/OpenSeesHpy.py
OpenSeesHpy/__init__.py
openseeshpy-0.1.1.dist-info/licenses/LICENSE
openseeshpy-0.1.1.dist-info/METADATA
openseeshpy-0.1.1.dist-info/WHEEL
openseeshpy-0.1.1.dist-info/top_level.txt
openseeshpy-0.1.1.dist-info/RECORD
