Metadata-Version: 2.4
Name: OpenSeesHpy
Version: 0.1.1
Summary: an OpenSees customization optimized for performance-based analysis and design of structures
Home-page: https://openseeshouse.com/
Author: OpesnSeesHouse
Author-email: OpesnSeesHouse <OpenSeesHouse@gmail.com>
License: MIT
Project-URL: Homepage, https://openseeshouse.com/
Project-URL: Repository, https://github.com/OpenSeesHouse/OpenSeesH
Requires-Python: ==3.13.*
License-File: LICENSE
Dynamic: author
Dynamic: home-page
Dynamic: license-file
Dynamic: requires-python
